LICENSE
README.md
setup.cfg
setup.py
Flask_Opsgenie.egg-info/PKG-INFO
Flask_Opsgenie.egg-info/SOURCES.txt
Flask_Opsgenie.egg-info/dependency_links.txt
Flask_Opsgenie.egg-info/not-zip-safe
Flask_Opsgenie.egg-info/requires.txt
Flask_Opsgenie.egg-info/top_level.txt
flask_opsgenie/__init__.py
flask_opsgenie/entities.py
flask_opsgenie/exceptions.py
flask_opsgenie/opsgenie.py
test/__init__.py
test/test_entities.py
test/test_opsgenie.py